<assembly
        xmlns="http://maven.apache.org/plugins/maven-assembly-plugin/assembly/1.1.0"
        xmlns:xsi="http://www.w3.org/2001/XMLSchema-instance"
        xsi:schemaLocation="http://maven.apache.org/plugins/maven-assembly-plugin/assembly/1.1.0 http://maven.apache.org/xsd/assembly-1.1.0.xsd">
    <id>jar-with-dependencies</id>
    <formats>
        <format>jar</format>
    </formats>
    <includeBaseDirectory>false</includeBaseDirectory>
    <containerDescriptorHandlers>
        <containerDescriptorHandler>
            <handlerName>metaInf-services</handlerName>
        </containerDescriptorHandler>
        <containerDescriptorHandler>
            <handlerName>file-aggregator</handlerName>
            <configuration>
                <filePattern>uk/ac/ebi/metingear/dialog-config.yml</filePattern>
                <outputPath>uk/ac/ebi/metingear/dialog-config.yml</outputPath>
            </configuration>
        </containerDescriptorHandler>
        <containerDescriptorHandler>
            <handlerName>file-aggregator</handlerName>
            <configuration>
                <filePattern>uk/ac/ebi/caf/action/action.properties
                </filePattern>
                <outputPath>uk/ac/ebi/caf/action/action.properties</outputPath>
            </configuration>
        </containerDescriptorHandler>
    </containerDescriptorHandlers>
    <dependencySets>
        <dependencySet>
            <outputDirectory>/</outputDirectory>
            <useProjectArtifact>true</useProjectArtifact>
            <unpack>true</unpack>
            <scope>runtime</scope>
            <excludes>
                <exclude>ilog.cplex:cplex</exclude>
            </excludes>
            <unpackOptions>
                <excludes>
                    <exclude>log4j.properties</exclude>
                    <exclude>simplelog.properties</exclude>
                    <exclude>*.javafiles</exclude>
                    <exclude>*.set</exclude>
                    <exclude>license/**</exclude>
                    <exclude>META-INF/liceneses</exclude>
                    <exclude>**/LICENSE*</exclude>
                    <exclude>**/NOTICE*</exclude>
                    <exclude>**/README*</exclude>
                </excludes>
            </unpackOptions>
        </dependencySet>
    </dependencySets>

</assembly>